{
  "$schema": "http://json-schema.org/draft-04/schema#",
  "type": "object",
  "properties": {
    "specification": {
      "type": "object",
      "properties": {
        "spec_name": {
          "type": "string"
        },
        "analytic": {
          "type": "integer"
        },
        "status_spec": {
          "type": "string"
        },
        "project": {
          "type": "integer"
        }
      },
      "required": [
        "spec_name",
        "analytic",
        "status_spec",
        "project"
      ]
    }
  },
  "required": [
    "specification"
  ]
}